codecrew/__init__.py
codecrew/cli.py
codecrew/communication.py
codecrew/execution.py
codecrew/main.py
codecrew/orchestrator.py
codecrew/templates.py
codecrew-1.1.1.dist-info/METADATA
codecrew-1.1.1.dist-info/WHEEL
codecrew-1.1.1.dist-info/entry_points.txt
codecrew-1.1.1.dist-info/RECORD
