Metadata-Version: 2.4
Name: codecrew
Version: 1.1.1
Summary: CodeCrew Multi-Agent Development System
Project-URL: Documentation, https://github.com/dscv101/codecrew#readme
Project-URL: Issues, https://github.com/dscv101/codecrew/issues
Project-URL: Source, https://github.com/dscv101/codecrew
Author-email: Derek Vitrano <derek@example.com>
License-Expression: MIT
Keywords: agents,ai,automation,cli,code-generation,development,fastapi,multi-agent
Classifier: Development Status :: 4 - Beta
Classifier: Environment :: Console
Classifier: Intended Audience :: Developers
Classifier: License :: OSI Approved :: MIT License
Classifier: Operating System :: OS Independent
Classifier: Programming Language :: Python :: 3
Classifier: Programming Language :: Python :: 3.11
Classifier: Programming Language :: Python :: 3.12
Classifier: Topic :: Software Development :: Code Generators
Classifier: Topic :: Software Development :: Libraries :: Application Frameworks
Classifier: Topic :: System :: Systems Administration
Requires-Python: >=3.11
Requires-Dist: alembic>=1.12.0
Requires-Dist: click>=8.1.0
Requires-Dist: fastapi>=0.104.0
Requires-Dist: jinja2>=3.1.0
Requires-Dist: passlib[bcrypt]>=1.7.4
Requires-Dist: psycopg2-binary>=2.9.0
Requires-Dist: pydantic>=2.0.0
Requires-Dist: python-dotenv>=1.0.0
Requires-Dist: python-jose[cryptography]>=3.3.0
Requires-Dist: python-multipart>=0.0.6
Requires-Dist: pyyaml>=6.0.0
Requires-Dist: redis>=5.0.0
Requires-Dist: requests>=2.31.0
Requires-Dist: rich>=13.6.0
Requires-Dist: sqlalchemy>=2.0.0
Requires-Dist: uvicorn[standard]>=0.24.0
Provides-Extra: dev
Requires-Dist: bandit>=1.7.0; extra == 'dev'
Requires-Dist: black>=23.0.0; extra == 'dev'
Requires-Dist: bump-my-version>=0.26.0; extra == 'dev'
Requires-Dist: flake8>=6.0.0; extra == 'dev'
Requires-Dist: httpx>=0.25.0; extra == 'dev'
Requires-Dist: isort>=5.12.0; extra == 'dev'
Requires-Dist: mypy>=1.6.0; extra == 'dev'
Requires-Dist: pip-audit>=2.6.0; extra == 'dev'
Requires-Dist: pre-commit>=3.4.0; extra == 'dev'
Requires-Dist: pytest-asyncio>=0.21.0; extra == 'dev'
Requires-Dist: pytest-cov>=4.1.0; extra == 'dev'
Requires-Dist: pytest>=7.4.0; extra == 'dev'
